

[{"MATERIAL_3D_ROTATION": "\uE84D",




"MATERIAL_AC_UNIT": "\uEB3B",




"MATERIAL_ACCESS_ALARM": "\uE190",




"MATERIAL_ACCESS_ALARMS": "\uE191",




"MATERIAL_ACCESS_TIME": "\uE192",




"MATERIAL_ACCESSIBILITY": "\uE84E",




"MATERIAL_ACCESSIBLE": "\uE914",




"MATERIAL_ACCOUNT_BALANCE": "\uE84F",




"MATERIAL_ACCOUNT_BALANCE_WALLET": "\uE850",




"MATERIAL_ACCOUNT_BOX": "\uE851",




"MATERIAL_ACCOUNT_CIRCLE": "\uE853",




"MATERIAL_ADB": "\uE60E",




"MATERIAL_ADD": "\uE145",




"MATERIAL_ADD_A_PHOTO": "\uE439",




"MATERIAL_ADD_ALARM": "\uE193",




"MATERIAL_ADD_ALERT": "\uE003",




"MATERIAL_ADD_BOX": "\uE146",




"MATERIAL_ADD_CIRCLE": "\uE147",




"MATERIAL_ADD_CIRCLE_OUTLINE": "\uE148",




"MATERIAL_ADD_LOCATION": "\uE567",




"MATERIAL_ADD_SHOPPING_CART": "\uE854",




"MATERIAL_ADD_TO_PHOTOS": "\uE39D",




"MATERIAL_ADD_TO_QUEUE": "\uE05C",




"MATERIAL_ADJUST": "\uE39E",




"MATERIAL_AIRLINE_SEAT_FLAT": "\uE630",




"MATERIAL_AIRLINE_SEAT_FLAT_ANGLED": "\uE631",




"MATERIAL_AIRLINE_SEAT_INDIVIDUAL_SUITE": "\uE632",




"MATERIAL_AIRLINE_SEAT_LEGROOM_EXTRA": "\uE633",




"MATERIAL_AIRLINE_SEAT_LEGROOM_NORMAL": "\uE634",




"MATERIAL_AIRLINE_SEAT_LEGROOM_REDUCED": "\uE635",




"MATERIAL_AIRLINE_SEAT_RECLINE_EXTRA": "\uE636",




"MATERIAL_AIRLINE_SEAT_RECLINE_NORMAL": "\uE637",




"MATERIAL_AIRPLANEMODE_ACTIVE": "\uE195",




"MATERIAL_AIRPLANEMODE_INACTIVE": "\uE194",




"MATERIAL_AIRPLAY": "\uE055",




"MATERIAL_AIRPORT_SHUTTLE": "\uEB3C",




"MATERIAL_ALARM": "\uE855",




"MATERIAL_ALARM_ADD": "\uE856",




"MATERIAL_ALARM_OFF": "\uE857",




"MATERIAL_ALARM_ON": "\uE858",




"MATERIAL_ALBUM": "\uE019",




"MATERIAL_ALL_INCLUSIVE": "\uEB3D",




"MATERIAL_ALL_OUT": "\uE90B",




"MATERIAL_ANDROID": "\uE859",




"MATERIAL_ANNOUNCEMENT": "\uE85A",




"MATERIAL_APPS": "\uE5C3",




"MATERIAL_ARCHIVE": "\uE149",




"MATERIAL_ARROW_BACK": "\uE5C4",




"MATERIAL_ARROW_DOWNWARD": "\uE5DB",




"MATERIAL_ARROW_DROP_DOWN": "\uE5C5",




"MATERIAL_ARROW_DROP_DOWN_CIRCLE": "\uE5C6",




"MATERIAL_ARROW_DROP_UP": "\uE5C7",




"MATERIAL_ARROW_FORWARD": "\uE5C8",




"MATERIAL_ARROW_UPWARD": "\uE5D8",




"MATERIAL_ART_TRACK": "\uE060",




"MATERIAL_ASPECT_RATIO": "\uE85B",




"MATERIAL_ASSESSMENT": "\uE85C",




"MATERIAL_ASSIGNMENT": "\uE85D",




"MATERIAL_ASSIGNMENT_IND": "\uE85E",




"MATERIAL_ASSIGNMENT_LATE": "\uE85F",




"MATERIAL_ASSIGNMENT_RETURN": "\uE860",




"MATERIAL_ASSIGNMENT_RETURNED": "\uE861",




"MATERIAL_ASSIGNMENT_TURNED_IN": "\uE862",




"MATERIAL_ASSISTANT": "\uE39F",




"MATERIAL_ASSISTANT_PHOTO": "\uE3A0",




"MATERIAL_ATTACH_FILE": "\uE226",




"MATERIAL_ATTACH_MONEY": "\uE227",




"MATERIAL_ATTACHMENT": "\uE2BC",




"MATERIAL_AUDIOTRACK": "\uE3A1",




"MATERIAL_AUTORENEW": "\uE863",




"MATERIAL_AV_TIMER": "\uE01B",




"MATERIAL_BACKSPACE": "\uE14A",




"MATERIAL_BACKUP": "\uE864",




"MATERIAL_BATTERY_ALERT": "\uE19C",




"MATERIAL_BATTERY_CHARGING_FULL": "\uE1A3",




"MATERIAL_BATTERY_FULL": "\uE1A4",




"MATERIAL_BATTERY_STD": "\uE1A5",




"MATERIAL_BATTERY_UNKNOWN": "\uE1A6",




"MATERIAL_BEACH_ACCESS": "\uEB3E",




"MATERIAL_BEENHERE": "\uE52D",




"MATERIAL_BLOCK": "\uE14B",




"MATERIAL_BLUETOOTH": "\uE1A7",




"MATERIAL_BLUETOOTH_AUDIO": "\uE60F",




"MATERIAL_BLUETOOTH_CONNECTED": "\uE1A8",




"MATERIAL_BLUETOOTH_DISABLED": "\uE1A9",




"MATERIAL_BLUETOOTH_SEARCHING": "\uE1AA",




"MATERIAL_BLUR_CIRCULAR": "\uE3A2",




"MATERIAL_BLUR_LINEAR": "\uE3A3",




"MATERIAL_BLUR_OFF": "\uE3A4",




"MATERIAL_BLUR_ON": "\uE3A5",




"MATERIAL_BOOK": "\uE865",




"MATERIAL_BOOKMARK": "\uE866",




"MATERIAL_BOOKMARK_BORDER": "\uE867",




"MATERIAL_BORDER_ALL": "\uE228",




"MATERIAL_BORDER_BOTTOM": "\uE229",




"MATERIAL_BORDER_CLEAR": "\uE22A",




"MATERIAL_BORDER_COLOR": "\uE22B",




"MATERIAL_BORDER_HORIZONTAL": "\uE22C",




"MATERIAL_BORDER_INNER": "\uE22D",




"MATERIAL_BORDER_LEFT": "\uE22E",




"MATERIAL_BORDER_OUTER": "\uE22F",




"MATERIAL_BORDER_RIGHT": "\uE230",




"MATERIAL_BORDER_STYLE": "\uE231",




"MATERIAL_BORDER_TOP": "\uE232",




"MATERIAL_BORDER_VERTICAL": "\uE233",




"MATERIAL_BRANDING_WATERMARK": "\uE06B",




"MATERIAL_BRIGHTNESS_1": "\uE3A6",




"MATERIAL_BRIGHTNESS_2": "\uE3A7",




"MATERIAL_BRIGHTNESS_3": "\uE3A8",




"MATERIAL_BRIGHTNESS_4": "\uE3A9",




"MATERIAL_BRIGHTNESS_5": "\uE3AA",




"MATERIAL_BRIGHTNESS_6": "\uE3AB",




"MATERIAL_BRIGHTNESS_7": "\uE3AC",




"MATERIAL_BRIGHTNESS_AUTO": "\uE1AB",




"MATERIAL_BRIGHTNESS_HIGH": "\uE1AC",




"MATERIAL_BRIGHTNESS_LOW": "\uE1AD",




"MATERIAL_BRIGHTNESS_MEDIUM": "\uE1AE",




"MATERIAL_BROKEN_IMAGE": "\uE3AD",




"MATERIAL_BRUSH": "\uE3AE",




"MATERIAL_BUBBLE_CHART": "\uE6DD",




"MATERIAL_BUG_REPORT": "\uE868",




"MATERIAL_BUILD": "\uE869",




"MATERIAL_BURST_MODE": "\uE43C",




"MATERIAL_BUSINESS": "\uE0AF",




"MATERIAL_BUSINESS_CENTER": "\uEB3F",




"MATERIAL_CACHED": "\uE86A",




"MATERIAL_CAKE": "\uE7E9",




"MATERIAL_CALL": "\uE0B0",




"MATERIAL_CALL_END": "\uE0B1",




"MATERIAL_CALL_MADE": "\uE0B2",




"MATERIAL_CALL_MERGE": "\uE0B3",




"MATERIAL_CALL_MISSED": "\uE0B4",




"MATERIAL_CALL_MISSED_OUTGOING": "\uE0E4",




"MATERIAL_CALL_RECEIVED": "\uE0B5",




"MATERIAL_CALL_SPLIT": "\uE0B6",




"MATERIAL_CALL_TO_ACTION": "\uE06C",




"MATERIAL_CAMERA": "\uE3AF",




"MATERIAL_CAMERA_ALT": "\uE3B0",




"MATERIAL_CAMERA_ENHANCE": "\uE8FC",




"MATERIAL_CAMERA_FRONT": "\uE3B1",




"MATERIAL_CAMERA_REAR": "\uE3B2",




"MATERIAL_CAMERA_ROLL": "\uE3B3",




"MATERIAL_CANCEL": "\uE5C9",




"MATERIAL_CARD_GIFTCARD": "\uE8F6",




"MATERIAL_CARD_MEMBERSHIP": "\uE8F7",




"MATERIAL_CARD_TRAVEL": "\uE8F8",




"MATERIAL_CASINO": "\uEB40",




"MATERIAL_CAST": "\uE307",




"MATERIAL_CAST_CONNECTED": "\uE308",




"MATERIAL_CENTER_FOCUS_STRONG": "\uE3B4",




"MATERIAL_CENTER_FOCUS_WEAK": "\uE3B5",




"MATERIAL_CHANGE_HISTORY": "\uE86B",




"MATERIAL_CHAT": "\uE0B7",




"MATERIAL_CHAT_BUBBLE": "\uE0CA",




"MATERIAL_CHAT_BUBBLE_OUTLINE": "\uE0CB",




"MATERIAL_CHECK": "\uE5CA",




"MATERIAL_CHECK_BOX": "\uE834",




"MATERIAL_CHECK_BOX_OUTLINE_BLANK": "\uE835",




"MATERIAL_CHECK_CIRCLE": "\uE86C",




"MATERIAL_CHEVRON_LEFT": "\uE5CB",




"MATERIAL_CHEVRON_RIGHT": "\uE5CC",




"MATERIAL_CHILD_CARE": "\uEB41",




"MATERIAL_CHILD_FRIENDLY": "\uEB42",




"MATERIAL_CHROME_READER_MODE": "\uE86D",




"MATERIAL_CLASS": "\uE86E",




"MATERIAL_CLEAR": "\uE14C",




"MATERIAL_CLEAR_ALL": "\uE0B8",




"MATERIAL_CLOSE": "\uE5CD",




"MATERIAL_CLOSED_CAPTION": "\uE01C",




"MATERIAL_CLOUD": "\uE2BD",




"MATERIAL_CLOUD_CIRCLE": "\uE2BE",




"MATERIAL_CLOUD_DONE": "\uE2BF",




"MATERIAL_CLOUD_DOWNLOAD": "\uE2C0",




"MATERIAL_CLOUD_OFF": "\uE2C1",




"MATERIAL_CLOUD_QUEUE": "\uE2C2",




"MATERIAL_CLOUD_UPLOAD": "\uE2C3",




"MATERIAL_CODE": "\uE86F",




"MATERIAL_COLLECTIONS": "\uE3B6",




"MATERIAL_COLLECTIONS_BOOKMARK": "\uE431",




"MATERIAL_COLOR_LENS": "\uE3B7",




"MATERIAL_COLORIZE": "\uE3B8",




"MATERIAL_COMMENT": "\uE0B9",




"MATERIAL_COMPARE": "\uE3B9",




"MATERIAL_COMPARE_ARROWS": "\uE915",




"MATERIAL_COMPUTER": "\uE30A",




"MATERIAL_CONFIRMATION_NUMBER": "\uE638",




"MATERIAL_CONTACT_MAIL": "\uE0D0",




"MATERIAL_CONTACT_PHONE": "\uE0CF",




"MATERIAL_CONTACTS": "\uE0BA",




"MATERIAL_CONTENT_COPY": "\uE14D",




"MATERIAL_CONTENT_CUT": "\uE14E",




"MATERIAL_CONTENT_PASTE": "\uE14F",




"MATERIAL_CONTROL_POINT": "\uE3BA",




"MATERIAL_CONTROL_POINT_DUPLICATE": "\uE3BB",




"MATERIAL_COPYRIGHT": "\uE90C",




"MATERIAL_CREATE": "\uE150",




"MATERIAL_CREATE_NEW_FOLDER": "\uE2CC",




"MATERIAL_CREDIT_CARD": "\uE870",




"MATERIAL_CROP": "\uE3BE",




"MATERIAL_CROP_16_9": "\uE3BC",




"MATERIAL_CROP_3_2": "\uE3BD",




"MATERIAL_CROP_5_4": "\uE3BF",




"MATERIAL_CROP_7_5": "\uE3C0",




"MATERIAL_CROP_DIN": "\uE3C1",




"MATERIAL_CROP_FREE": "\uE3C2",




"MATERIAL_CROP_LANDSCAPE": "\uE3C3",




"MATERIAL_CROP_ORIGINAL": "\uE3C4",




"MATERIAL_CROP_PORTRAIT": "\uE3C5",




"MATERIAL_CROP_ROTATE": "\uE437",




"MATERIAL_CROP_SQUARE": "\uE3C6",




"MATERIAL_DASHBOARD": "\uE871",




"MATERIAL_DATA_USAGE": "\uE1AF",




"MATERIAL_DATE_RANGE": "\uE916",




"MATERIAL_DEHAZE": "\uE3C7",




"MATERIAL_DELETE": "\uE872",




"MATERIAL_DELETE_FOREVER": "\uE92B",




"MATERIAL_DELETE_SWEEP": "\uE16C",




"MATERIAL_DESCRIPTION": "\uE873",




"MATERIAL_DESKTOP_MAC": "\uE30B",




"MATERIAL_DESKTOP_WINDOWS": "\uE30C",




"MATERIAL_DETAILS": "\uE3C8",




"MATERIAL_DEVELOPER_BOARD": "\uE30D",




"MATERIAL_DEVELOPER_MODE": "\uE1B0",




"MATERIAL_DEVICE_HUB": "\uE335",




"MATERIAL_DEVICES": "\uE1B1",




"MATERIAL_DEVICES_OTHER": "\uE337",




"MATERIAL_DIALER_SIP": "\uE0BB",




"MATERIAL_DIALPAD": "\uE0BC",




"MATERIAL_DIRECTIONS": "\uE52E",




"MATERIAL_DIRECTIONS_BIKE": "\uE52F",




"MATERIAL_DIRECTIONS_BOAT": "\uE532",




"MATERIAL_DIRECTIONS_BUS": "\uE530",




"MATERIAL_DIRECTIONS_CAR": "\uE531",




"MATERIAL_DIRECTIONS_RAILWAY": "\uE534",




"MATERIAL_DIRECTIONS_RUN": "\uE566",




"MATERIAL_DIRECTIONS_SUBWAY": "\uE533",




"MATERIAL_DIRECTIONS_TRANSIT": "\uE535",




"MATERIAL_DIRECTIONS_WALK": "\uE536",




"MATERIAL_DISC_FULL": "\uE610",




"MATERIAL_DNS": "\uE875",




"MATERIAL_DO_NOT_DISTURB": "\uE612",




"MATERIAL_DO_NOT_DISTURB_ALT": "\uE611",




"MATERIAL_DO_NOT_DISTURB_OFF": "\uE643",




"MATERIAL_DO_NOT_DISTURB_ON": "\uE644",




"MATERIAL_DOCK": "\uE30E",




"MATERIAL_DOMAIN": "\uE7EE",




"MATERIAL_DONE": "\uE876",




"MATERIAL_DONE_ALL": "\uE877",




"MATERIAL_DONUT_LARGE": "\uE917",




"MATERIAL_DONUT_SMALL": "\uE918",




"MATERIAL_DRAFTS": "\uE151",




"MATERIAL_DRAG_HANDLE": "\uE25D",




"MATERIAL_DRIVE_ETA": "\uE613",




"MATERIAL_DVR": "\uE1B2",




"MATERIAL_EDIT": "\uE3C9",




"MATERIAL_EDIT_LOCATION": "\uE568",




"MATERIAL_EJECT": "\uE8FB",




"MATERIAL_EMAIL": "\uE0BE",




"MATERIAL_ENHANCED_ENCRYPTION": "\uE63F",




"MATERIAL_EQUALIZER": "\uE01D",




"MATERIAL_ERROR": "\uE000",




"MATERIAL_ERROR_OUTLINE": "\uE001",




"MATERIAL_EURO_SYMBOL": "\uE926",




"MATERIAL_EV_STATION": "\uE56D",




"MATERIAL_EVENT": "\uE878",




"MATERIAL_EVENT_AVAILABLE": "\uE614",




"MATERIAL_EVENT_BUSY": "\uE615",




"MATERIAL_EVENT_NOTE": "\uE616",




"MATERIAL_EVENT_SEAT": "\uE903",




"MATERIAL_EXIT_TO_APP": "\uE879",




"MATERIAL_EXPAND_LESS": "\uE5CE",




"MATERIAL_EXPAND_MORE": "\uE5CF",




"MATERIAL_EXPLICIT": "\uE01E",




"MATERIAL_EXPLORE": "\uE87A",




"MATERIAL_EXPOSURE": "\uE3CA",




"MATERIAL_EXPOSURE_NEG_1": "\uE3CB",




"MATERIAL_EXPOSURE_NEG_2": "\uE3CC",




"MATERIAL_EXPOSURE_PLUS_1": "\uE3CD",




"MATERIAL_EXPOSURE_PLUS_2": "\uE3CE",




"MATERIAL_EXPOSURE_ZERO": "\uE3CF",




"MATERIAL_EXTENSION": "\uE87B",




"MATERIAL_FACE": "\uE87C",




"MATERIAL_FAST_FORWARD": "\uE01F",




"MATERIAL_FAST_REWIND": "\uE020",




"MATERIAL_FAVORITE": "\uE87D",




"MATERIAL_FAVORITE_BORDER": "\uE87E",




"MATERIAL_FEATURED_PLAY_LIST": "\uE06D",




"MATERIAL_FEATURED_VIDEO": "\uE06E",




"MATERIAL_FEEDBACK": "\uE87F",




"MATERIAL_FIBER_DVR": "\uE05D",




"MATERIAL_FIBER_MANUAL_RECORD": "\uE061",




"MATERIAL_FIBER_NEW": "\uE05E",




"MATERIAL_FIBER_PIN": "\uE06A",




"MATERIAL_FIBER_SMART_RECORD": "\uE062",




"MATERIAL_FILE_DOWNLOAD": "\uE2C4",




"MATERIAL_FILE_UPLOAD": "\uE2C6",




"MATERIAL_FILTER": "\uE3D3",




"MATERIAL_FILTER_1": "\uE3D0",




"MATERIAL_FILTER_2": "\uE3D1",




"MATERIAL_FILTER_3": "\uE3D2",




"MATERIAL_FILTER_4": "\uE3D4",




"MATERIAL_FILTER_5": "\uE3D5",




"MATERIAL_FILTER_6": "\uE3D6",




"MATERIAL_FILTER_7": "\uE3D7",




"MATERIAL_FILTER_8": "\uE3D8",




"MATERIAL_FILTER_9": "\uE3D9",




"MATERIAL_FILTER_9_PLUS": "\uE3DA",




"MATERIAL_FILTER_B_AND_W": "\uE3DB",




"MATERIAL_FILTER_CENTER_FOCUS": "\uE3DC",




"MATERIAL_FILTER_DRAMA": "\uE3DD",




"MATERIAL_FILTER_FRAMES": "\uE3DE",




"MATERIAL_FILTER_HDR": "\uE3DF",




"MATERIAL_FILTER_LIST": "\uE152",




"MATERIAL_FILTER_NONE": "\uE3E0",




"MATERIAL_FILTER_TILT_SHIFT": "\uE3E2",




"MATERIAL_FILTER_VINTAGE": "\uE3E3",




"MATERIAL_FIND_IN_PAGE": "\uE880",




"MATERIAL_FIND_REPLACE": "\uE881",




"MATERIAL_FINGERPRINT": "\uE90D",




"MATERIAL_FIRST_PAGE": "\uE5DC",




"MATERIAL_FITNESS_CENTER": "\uEB43",




"MATERIAL_FLAG": "\uE153",




"MATERIAL_FLARE": "\uE3E4",




"MATERIAL_FLASH_AUTO": "\uE3E5",




"MATERIAL_FLASH_OFF": "\uE3E6",




"MATERIAL_FLASH_ON": "\uE3E7",




"MATERIAL_FLIGHT": "\uE539",




"MATERIAL_FLIGHT_LAND": "\uE904",




"MATERIAL_FLIGHT_TAKEOFF": "\uE905",




"MATERIAL_FLIP": "\uE3E8",




"MATERIAL_FLIP_TO_BACK": "\uE882",




"MATERIAL_FLIP_TO_FRONT": "\uE883",




"MATERIAL_FOLDER": "\uE2C7",




"MATERIAL_FOLDER_OPEN": "\uE2C8",




"MATERIAL_FOLDER_SHARED": "\uE2C9",




"MATERIAL_FOLDER_SPECIAL": "\uE617",




"MATERIAL_FONT_DOWNLOAD": "\uE167",




"MATERIAL_FORMAT_ALIGN_CENTER": "\uE234",




"MATERIAL_FORMAT_ALIGN_JUSTIFY": "\uE235",




"MATERIAL_FORMAT_ALIGN_LEFT": "\uE236",




"MATERIAL_FORMAT_ALIGN_RIGHT": "\uE237",




"MATERIAL_FORMAT_BOLD": "\uE238",




"MATERIAL_FORMAT_CLEAR": "\uE239",




"MATERIAL_FORMAT_COLOR_FILL": "\uE23A",




"MATERIAL_FORMAT_COLOR_RESET": "\uE23B",




"MATERIAL_FORMAT_COLOR_TEXT": "\uE23C",




"MATERIAL_FORMAT_INDENT_DECREASE": "\uE23D",




"MATERIAL_FORMAT_INDENT_INCREASE": "\uE23E",




"MATERIAL_FORMAT_ITALIC": "\uE23F",




"MATERIAL_FORMAT_LINE_SPACING": "\uE240",




"MATERIAL_FORMAT_LIST_BULLETED": "\uE241",




"MATERIAL_FORMAT_LIST_NUMBERED": "\uE242",




"MATERIAL_FORMAT_PAINT": "\uE243",




"MATERIAL_FORMAT_QUOTE": "\uE244",




"MATERIAL_FORMAT_SHAPES": "\uE25E",




"MATERIAL_FORMAT_SIZE": "\uE245",




"MATERIAL_FORMAT_STRIKETHROUGH": "\uE246",




"MATERIAL_FORMAT_TEXTDIRECTION_L_TO_R": "\uE247",




"MATERIAL_FORMAT_TEXTDIRECTION_R_TO_L": "\uE248",




"MATERIAL_FORMAT_UNDERLINED": "\uE249",




"MATERIAL_FORUM": "\uE0BF",




"MATERIAL_FORWARD": "\uE154",




"MATERIAL_FORWARD_10": "\uE056",




"MATERIAL_FORWARD_30": "\uE057",




"MATERIAL_FORWARD_5": "\uE058",




"MATERIAL_FREE_BREAKFAST": "\uEB44",




"MATERIAL_FULLSCREEN": "\uE5D0",




"MATERIAL_FULLSCREEN_EXIT": "\uE5D1",




"MATERIAL_FUNCTIONS": "\uE24A",




"MATERIAL_G_TRANSLATE": "\uE927",




"MATERIAL_GAMEPAD": "\uE30F",




"MATERIAL_GAMES": "\uE021",




"MATERIAL_GAVEL": "\uE90E",




"MATERIAL_GESTURE": "\uE155",




"MATERIAL_GET_APP": "\uE884",




"MATERIAL_GIF": "\uE908",




"MATERIAL_GOLF_COURSE": "\uEB45",




"MATERIAL_GPS_FIXED": "\uE1B3",




"MATERIAL_GPS_NOT_FIXED": "\uE1B4",




"MATERIAL_GPS_OFF": "\uE1B5",




"MATERIAL_GRADE": "\uE885",




"MATERIAL_GRADIENT": "\uE3E9",




"MATERIAL_GRAIN": "\uE3EA",




"MATERIAL_GRAPHIC_EQ": "\uE1B8",




"MATERIAL_GRID_OFF": "\uE3EB",




"MATERIAL_GRID_ON": "\uE3EC",




"MATERIAL_GROUP": "\uE7EF",




"MATERIAL_GROUP_ADD": "\uE7F0",




"MATERIAL_GROUP_WORK": "\uE886",




"MATERIAL_HD": "\uE052",




"MATERIAL_HDR_OFF": "\uE3ED",




"MATERIAL_HDR_ON": "\uE3EE",




"MATERIAL_HDR_STRONG": "\uE3F1",




"MATERIAL_HDR_WEAK": "\uE3F2",




"MATERIAL_HEADSET": "\uE310",




"MATERIAL_HEADSET_MIC": "\uE311",




"MATERIAL_HEALING": "\uE3F3",




"MATERIAL_HEARING": "\uE023",




"MATERIAL_HELP": "\uE887",




"MATERIAL_HELP_OUTLINE": "\uE8FD",




"MATERIAL_HIGH_QUALITY": "\uE024",




"MATERIAL_HIGHLIGHT": "\uE25F",




"MATERIAL_HIGHLIGHT_OFF": "\uE888",




"MATERIAL_HISTORY": "\uE889",




"MATERIAL_HOME": "\uE88A",




"MATERIAL_HOT_TUB": "\uEB46",




"MATERIAL_HOTEL": "\uE53A",




"MATERIAL_HOURGLASS_EMPTY": "\uE88B",




"MATERIAL_HOURGLASS_FULL": "\uE88C",




"MATERIAL_HTTP": "\uE902",




"MATERIAL_HTTPS": "\uE88D",




"MATERIAL_IMAGE": "\uE3F4",




"MATERIAL_IMAGE_ASPECT_RATIO": "\uE3F5",




"MATERIAL_IMPORT_CONTACTS": "\uE0E0",




"MATERIAL_IMPORT_EXPORT": "\uE0C3",




"MATERIAL_IMPORTANT_DEVICES": "\uE912",




"MATERIAL_INBOX": "\uE156",




"MATERIAL_INDETERMINATE_CHECK_BOX": "\uE909",




"MATERIAL_INFO": "\uE88E",




"MATERIAL_INFO_OUTLINE": "\uE88F",




"MATERIAL_INPUT": "\uE890",




"MATERIAL_INSERT_CHART": "\uE24B",




"MATERIAL_INSERT_COMMENT": "\uE24C",




"MATERIAL_INSERT_DRIVE_FILE": "\uE24D",




"MATERIAL_INSERT_EMOTICON": "\uE24E",




"MATERIAL_INSERT_INVITATION": "\uE24F",




"MATERIAL_INSERT_LINK": "\uE250",




"MATERIAL_INSERT_PHOTO": "\uE251",




"MATERIAL_INVERT_COLORS": "\uE891",




"MATERIAL_INVERT_COLORS_OFF": "\uE0C4",




"MATERIAL_ISO": "\uE3F6",




"MATERIAL_KEYBOARD": "\uE312",




"MATERIAL_KEYBOARD_ARROW_DOWN": "\uE313",




"MATERIAL_KEYBOARD_ARROW_LEFT": "\uE314",




"MATERIAL_KEYBOARD_ARROW_RIGHT": "\uE315",




"MATERIAL_KEYBOARD_ARROW_UP": "\uE316",




"MATERIAL_KEYBOARD_BACKSPACE": "\uE317",




"MATERIAL_KEYBOARD_CAPSLOCK": "\uE318",




"MATERIAL_KEYBOARD_HIDE": "\uE31A",




"MATERIAL_KEYBOARD_RETURN": "\uE31B",




"MATERIAL_KEYBOARD_TAB": "\uE31C",




"MATERIAL_KEYBOARD_VOICE": "\uE31D",




"MATERIAL_KITCHEN": "\uEB47",




"MATERIAL_LABEL": "\uE892",




"MATERIAL_LABEL_OUTLINE": "\uE893",




"MATERIAL_LANDSCAPE": "\uE3F7",




"MATERIAL_LANGUAGE": "\uE894",




"MATERIAL_LAPTOP": "\uE31E",




"MATERIAL_LAPTOP_CHROMEBOOK": "\uE31F",




"MATERIAL_LAPTOP_MAC": "\uE320",




"MATERIAL_LAPTOP_WINDOWS": "\uE321",




"MATERIAL_LAST_PAGE": "\uE5DD",




"MATERIAL_LAUNCH": "\uE895",




"MATERIAL_LAYERS": "\uE53B",




"MATERIAL_LAYERS_CLEAR": "\uE53C",




"MATERIAL_LEAK_ADD": "\uE3F8",




"MATERIAL_LEAK_REMOVE": "\uE3F9",




"MATERIAL_LENS": "\uE3FA",




"MATERIAL_LIBRARY_ADD": "\uE02E",




"MATERIAL_LIBRARY_BOOKS": "\uE02F",




"MATERIAL_LIBRARY_MUSIC": "\uE030",




"MATERIAL_LIGHTBULB_OUTLINE": "\uE90F",




"MATERIAL_LINE_STYLE": "\uE919",




"MATERIAL_LINE_WEIGHT": "\uE91A",




"MATERIAL_LINEAR_SCALE": "\uE260",




"MATERIAL_LINK": "\uE157",




"MATERIAL_LINKED_CAMERA": "\uE438",




"MATERIAL_LIST": "\uE896",




"MATERIAL_LIVE_HELP": "\uE0C6",




"MATERIAL_LIVE_TV": "\uE639",




"MATERIAL_LOCAL_ACTIVITY": "\uE53F",




"MATERIAL_LOCAL_AIRPORT": "\uE53D",




"MATERIAL_LOCAL_ATM": "\uE53E",




"MATERIAL_LOCAL_BAR": "\uE540",




"MATERIAL_LOCAL_CAFE": "\uE541",




"MATERIAL_LOCAL_CAR_WASH": "\uE542",




"MATERIAL_LOCAL_CONVENIENCE_STORE": "\uE543",




"MATERIAL_LOCAL_DINING": "\uE556",




"MATERIAL_LOCAL_DRINK": "\uE544",




"MATERIAL_LOCAL_FLORIST": "\uE545",




"MATERIAL_LOCAL_GAS_STATION": "\uE546",




"MATERIAL_LOCAL_GROCERY_STORE": "\uE547",




"MATERIAL_LOCAL_HOSPITAL": "\uE548",




"MATERIAL_LOCAL_HOTEL": "\uE549",




"MATERIAL_LOCAL_LAUNDRY_SERVICE": "\uE54A",




"MATERIAL_LOCAL_LIBRARY": "\uE54B",




"MATERIAL_LOCAL_MALL": "\uE54C",




"MATERIAL_LOCAL_MOVIES": "\uE54D",




"MATERIAL_LOCAL_OFFER": "\uE54E",




"MATERIAL_LOCAL_PARKING": "\uE54F",




"MATERIAL_LOCAL_PHARMACY": "\uE550",




"MATERIAL_LOCAL_PHONE": "\uE551",




"MATERIAL_LOCAL_PIZZA": "\uE552",




"MATERIAL_LOCAL_PLAY": "\uE553",




"MATERIAL_LOCAL_POST_OFFICE": "\uE554",




"MATERIAL_LOCAL_PRINTSHOP": "\uE555",




"MATERIAL_LOCAL_SEE": "\uE557",




"MATERIAL_LOCAL_SHIPPING": "\uE558",




"MATERIAL_LOCAL_TAXI": "\uE559",




"MATERIAL_LOCATION_CITY": "\uE7F1",




"MATERIAL_LOCATION_DISABLED": "\uE1B6",




"MATERIAL_LOCATION_OFF": "\uE0C7",




"MATERIAL_LOCATION_ON": "\uE0C8",




"MATERIAL_LOCATION_SEARCHING": "\uE1B7",




"MATERIAL_LOCK": "\uE897",




"MATERIAL_LOCK_OPEN": "\uE898",




"MATERIAL_LOCK_OUTLINE": "\uE899",




"MATERIAL_LOOKS": "\uE3FC",




"MATERIAL_LOOKS_3": "\uE3FB",




"MATERIAL_LOOKS_4": "\uE3FD",




"MATERIAL_LOOKS_5": "\uE3FE",




"MATERIAL_LOOKS_6": "\uE3FF",




"MATERIAL_LOOKS_ONE": "\uE400",




"MATERIAL_LOOKS_TWO": "\uE401",




"MATERIAL_LOOP": "\uE028",




"MATERIAL_LOUPE": "\uE402",




"MATERIAL_LOW_PRIORITY": "\uE16D",




"MATERIAL_LOYALTY": "\uE89A",




"MATERIAL_MAIL": "\uE158",




"MATERIAL_MAIL_OUTLINE": "\uE0E1",




"MATERIAL_MAP": "\uE55B",




"MATERIAL_MARKUNREAD": "\uE159",




"MATERIAL_MARKUNREAD_MAILBOX": "\uE89B",




"MATERIAL_MEMORY": "\uE322",




"MATERIAL_MENU": "\uE5D2",




"MATERIAL_MERGE_TYPE": "\uE252",




"MATERIAL_MESSAGE": "\uE0C9",




"MATERIAL_MIC": "\uE029",




"MATERIAL_MIC_NONE": "\uE02A",




"MATERIAL_MIC_OFF": "\uE02B",




"MATERIAL_MMS": "\uE618",




"MATERIAL_MODE_COMMENT": "\uE253",




"MATERIAL_MODE_EDIT": "\uE254",




"MATERIAL_MONETIZATION_ON": "\uE263",




"MATERIAL_MONEY_OFF": "\uE25C",




"MATERIAL_MONOCHROME_PHOTOS": "\uE403",




"MATERIAL_MOOD": "\uE7F2",




"MATERIAL_MOOD_BAD": "\uE7F3",




"MATERIAL_MORE": "\uE619",




"MATERIAL_MORE_HORIZ": "\uE5D3",




"MATERIAL_MORE_VERT": "\uE5D4",




"MATERIAL_MOTORCYCLE": "\uE91B",




"MATERIAL_MOUSE": "\uE323",




"MATERIAL_MOVE_TO_INBOX": "\uE168",




"MATERIAL_MOVIE": "\uE02C",




"MATERIAL_MOVIE_CREATION": "\uE404",




"MATERIAL_MOVIE_FILTER": "\uE43A",




"MATERIAL_MULTILINE_CHART": "\uE6DF",




"MATERIAL_MUSIC_NOTE": "\uE405",




"MATERIAL_MUSIC_VIDEO": "\uE063",




"MATERIAL_MY_LOCATION": "\uE55C",




"MATERIAL_NATURE": "\uE406",




"MATERIAL_NATURE_PEOPLE": "\uE407",




"MATERIAL_NAVIGATE_BEFORE": "\uE408",




"MATERIAL_NAVIGATE_NEXT": "\uE409",




"MATERIAL_NAVIGATION": "\uE55D",




"MATERIAL_NEAR_ME": "\uE569",




"MATERIAL_NETWORK_CELL": "\uE1B9",




"MATERIAL_NETWORK_CHECK": "\uE640",




"MATERIAL_NETWORK_LOCKED": "\uE61A",




"MATERIAL_NETWORK_WIFI": "\uE1BA",




"MATERIAL_NEW_RELEASES": "\uE031",




"MATERIAL_NEXT_WEEK": "\uE16A",




"MATERIAL_NFC": "\uE1BB",




"MATERIAL_NO_ENCRYPTION": "\uE641",




"MATERIAL_NO_SIM": "\uE0CC",




"MATERIAL_NOT_INTERESTED": "\uE033",




"MATERIAL_NOTE": "\uE06F",




"MATERIAL_NOTE_ADD": "\uE89C",




"MATERIAL_NOTIFICATIONS": "\uE7F4",




"MATERIAL_NOTIFICATIONS_ACTIVE": "\uE7F7",




"MATERIAL_NOTIFICATIONS_NONE": "\uE7F5",




"MATERIAL_NOTIFICATIONS_OFF": "\uE7F6",




"MATERIAL_NOTIFICATIONS_PAUSED": "\uE7F8",




"MATERIAL_OFFLINE_PIN": "\uE90A",




"MATERIAL_ONDEMAND_VIDEO": "\uE63A",




"MATERIAL_OPACITY": "\uE91C",




"MATERIAL_OPEN_IN_BROWSER": "\uE89D",




"MATERIAL_OPEN_IN_NEW": "\uE89E",




"MATERIAL_OPEN_WITH": "\uE89F",




"MATERIAL_PAGES": "\uE7F9",




"MATERIAL_PAGEVIEW": "\uE8A0",




"MATERIAL_PALETTE": "\uE40A",




"MATERIAL_PAN_TOOL": "\uE925",




"MATERIAL_PANORAMA": "\uE40B",




"MATERIAL_PANORAMA_FISH_EYE": "\uE40C",




"MATERIAL_PANORAMA_HORIZONTAL": "\uE40D",




"MATERIAL_PANORAMA_VERTICAL": "\uE40E",




"MATERIAL_PANORAMA_WIDE_ANGLE": "\uE40F",




"MATERIAL_PARTY_MODE": "\uE7FA",




"MATERIAL_PAUSE": "\uE034",




"MATERIAL_PAUSE_CIRCLE_FILLED": "\uE035",




"MATERIAL_PAUSE_CIRCLE_OUTLINE": "\uE036",




"MATERIAL_PAYMENT": "\uE8A1",




"MATERIAL_PEOPLE": "\uE7FB",




"MATERIAL_PEOPLE_OUTLINE": "\uE7FC",




"MATERIAL_PERM_CAMERA_MIC": "\uE8A2",




"MATERIAL_PERM_CONTACT_CALENDAR": "\uE8A3",




"MATERIAL_PERM_DATA_SETTING": "\uE8A4",




"MATERIAL_PERM_DEVICE_INFORMATION": "\uE8A5",




"MATERIAL_PERM_IDENTITY": "\uE8A6",




"MATERIAL_PERM_MEDIA": "\uE8A7",




"MATERIAL_PERM_PHONE_MSG": "\uE8A8",




"MATERIAL_PERM_SCAN_WIFI": "\uE8A9",




"MATERIAL_PERSON": "\uE7FD",




"MATERIAL_PERSON_ADD": "\uE7FE",




"MATERIAL_PERSON_OUTLINE": "\uE7FF",




"MATERIAL_PERSON_PIN": "\uE55A",




"MATERIAL_PERSON_PIN_CIRCLE": "\uE56A",




"MATERIAL_PERSONAL_VIDEO": "\uE63B",




"MATERIAL_PETS": "\uE91D",




"MATERIAL_PHONE": "\uE0CD",




"MATERIAL_PHONE_ANDROID": "\uE324",




"MATERIAL_PHONE_BLUETOOTH_SPEAKER": "\uE61B",




"MATERIAL_PHONE_FORWARDED": "\uE61C",




"MATERIAL_PHONE_IN_TALK": "\uE61D",




"MATERIAL_PHONE_IPHONE": "\uE325",




"MATERIAL_PHONE_LOCKED": "\uE61E",




"MATERIAL_PHONE_MISSED": "\uE61F",




"MATERIAL_PHONE_PAUSED": "\uE620",




"MATERIAL_PHONELINK": "\uE326",




"MATERIAL_PHONELINK_ERASE": "\uE0DB",




"MATERIAL_PHONELINK_LOCK": "\uE0DC",




"MATERIAL_PHONELINK_OFF": "\uE327",




"MATERIAL_PHONELINK_RING": "\uE0DD",




"MATERIAL_PHONELINK_SETUP": "\uE0DE",




"MATERIAL_PHOTO": "\uE410",




"MATERIAL_PHOTO_ALBUM": "\uE411",




"MATERIAL_PHOTO_CAMERA": "\uE412",




"MATERIAL_PHOTO_FILTER": "\uE43B",




"MATERIAL_PHOTO_LIBRARY": "\uE413",




"MATERIAL_PHOTO_SIZE_SELECT_ACTUAL": "\uE432",




"MATERIAL_PHOTO_SIZE_SELECT_LARGE": "\uE433",




"MATERIAL_PHOTO_SIZE_SELECT_SMALL": "\uE434",




"MATERIAL_PICTURE_AS_PDF": "\uE415",




"MATERIAL_PICTURE_IN_PICTURE": "\uE8AA",




"MATERIAL_PICTURE_IN_PICTURE_ALT": "\uE911",




"MATERIAL_PIE_CHART": "\uE6C4",




"MATERIAL_PIE_CHART_OUTLINED": "\uE6C5",




"MATERIAL_PIN_DROP": "\uE55E",




"MATERIAL_PLACE": "\uE55F",




"MATERIAL_PLAY_ARROW": "\uE037",




"MATERIAL_PLAY_CIRCLE_FILLED": "\uE038",




"MATERIAL_PLAY_CIRCLE_OUTLINE": "\uE039",




"MATERIAL_PLAY_FOR_WORK": "\uE906",




"MATERIAL_PLAYLIST_ADD": "\uE03B",




"MATERIAL_PLAYLIST_ADD_CHECK": "\uE065",




"MATERIAL_PLAYLIST_PLAY": "\uE05F",




"MATERIAL_PLUS_ONE": "\uE800",




"MATERIAL_POLL": "\uE801",




"MATERIAL_POLYMER": "\uE8AB",




"MATERIAL_POOL": "\uEB48",




"MATERIAL_PORTABLE_WIFI_OFF": "\uE0CE",




"MATERIAL_PORTRAIT": "\uE416",




"MATERIAL_POWER": "\uE63C",




"MATERIAL_POWER_INPUT": "\uE336",




"MATERIAL_POWER_SETTINGS_NEW": "\uE8AC",




"MATERIAL_PREGNANT_WOMAN": "\uE91E",




"MATERIAL_PRESENT_TO_ALL": "\uE0DF",




"MATERIAL_PRINT": "\uE8AD",




"MATERIAL_PRIORITY_HIGH": "\uE645",




"MATERIAL_PUBLIC": "\uE80B",




"MATERIAL_PUBLISH": "\uE255",




"MATERIAL_QUERY_BUILDER": "\uE8AE",




"MATERIAL_QUESTION_ANSWER": "\uE8AF",




"MATERIAL_QUEUE": "\uE03C",




"MATERIAL_QUEUE_MUSIC": "\uE03D",




"MATERIAL_QUEUE_PLAY_NEXT": "\uE066",




"MATERIAL_RADIO": "\uE03E",




"MATERIAL_RADIO_BUTTON_CHECKED": "\uE837",




"MATERIAL_RADIO_BUTTON_UNCHECKED": "\uE836",




"MATERIAL_RATE_REVIEW": "\uE560",




"MATERIAL_RECEIPT": "\uE8B0",




"MATERIAL_RECENT_ACTORS": "\uE03F",




"MATERIAL_RECORD_VOICE_OVER": "\uE91F",




"MATERIAL_REDEEM": "\uE8B1",




"MATERIAL_REDO": "\uE15A",




"MATERIAL_REFRESH": "\uE5D5",




"MATERIAL_REMOVE": "\uE15B",




"MATERIAL_REMOVE_CIRCLE": "\uE15C",




"MATERIAL_REMOVE_CIRCLE_OUTLINE": "\uE15D",




"MATERIAL_REMOVE_FROM_QUEUE": "\uE067",




"MATERIAL_REMOVE_RED_EYE": "\uE417",




"MATERIAL_REMOVE_SHOPPING_CART": "\uE928",




"MATERIAL_REORDER": "\uE8FE",




"MATERIAL_REPEAT": "\uE040",




"MATERIAL_REPEAT_ONE": "\uE041",




"MATERIAL_REPLAY": "\uE042",




"MATERIAL_REPLAY_10": "\uE059",




"MATERIAL_REPLAY_30": "\uE05A",




"MATERIAL_REPLAY_5": "\uE05B",




"MATERIAL_REPLY": "\uE15E",




"MATERIAL_REPLY_ALL": "\uE15F",




"MATERIAL_REPORT": "\uE160",




"MATERIAL_REPORT_PROBLEM": "\uE8B2",




"MATERIAL_RESTAURANT": "\uE56C",




"MATERIAL_RESTAURANT_MENU": "\uE561",




"MATERIAL_RESTORE": "\uE8B3",




"MATERIAL_RESTORE_PAGE": "\uE929",




"MATERIAL_RING_VOLUME": "\uE0D1",




"MATERIAL_ROOM": "\uE8B4",




"MATERIAL_ROOM_SERVICE": "\uEB49",




"MATERIAL_ROTATE_90_DEGREES_CCW": "\uE418",




"MATERIAL_ROTATE_LEFT": "\uE419",




"MATERIAL_ROTATE_RIGHT": "\uE41A",




"MATERIAL_ROUNDED_CORNER": "\uE920",




"MATERIAL_ROUTER": "\uE328",




"MATERIAL_ROWING": "\uE921",




"MATERIAL_RSS_FEED": "\uE0E5",




"MATERIAL_RV_HOOKUP": "\uE642",




"MATERIAL_SATELLITE": "\uE562",




"MATERIAL_SAVE": "\uE161",




"MATERIAL_SCANNER": "\uE329",




"MATERIAL_SCHEDULE": "\uE8B5",




"MATERIAL_SCHOOL": "\uE80C",




"MATERIAL_SCREEN_LOCK_LANDSCAPE": "\uE1BE",




"MATERIAL_SCREEN_LOCK_PORTRAIT": "\uE1BF",




"MATERIAL_SCREEN_LOCK_ROTATION": "\uE1C0",




"MATERIAL_SCREEN_ROTATION": "\uE1C1",




"MATERIAL_SCREEN_SHARE": "\uE0E2",




"MATERIAL_SD_CARD": "\uE623",




"MATERIAL_SD_STORAGE": "\uE1C2",




"MATERIAL_SEARCH": "\uE8B6",




"MATERIAL_SECURITY": "\uE32A",




"MATERIAL_SELECT_ALL": "\uE162",




"MATERIAL_SEND": "\uE163",




"MATERIAL_SENTIMENT_DISSATISFIED": "\uE811",




"MATERIAL_SENTIMENT_NEUTRAL": "\uE812",




"MATERIAL_SENTIMENT_SATISFIED": "\uE813",




"MATERIAL_SENTIMENT_VERY_DISSATISFIED": "\uE814",




"MATERIAL_SENTIMENT_VERY_SATISFIED": "\uE815",




"MATERIAL_SETTINGS": "\uE8B8",




"MATERIAL_SETTINGS_APPLICATIONS": "\uE8B9",




"MATERIAL_SETTINGS_BACKUP_RESTORE": "\uE8BA",




"MATERIAL_SETTINGS_BLUETOOTH": "\uE8BB",




"MATERIAL_SETTINGS_BRIGHTNESS": "\uE8BD",




"MATERIAL_SETTINGS_CELL": "\uE8BC",




"MATERIAL_SETTINGS_ETHERNET": "\uE8BE",




"MATERIAL_SETTINGS_INPUT_ANTENNA": "\uE8BF",




"MATERIAL_SETTINGS_INPUT_COMPONENT": "\uE8C0",




"MATERIAL_SETTINGS_INPUT_COMPOSITE": "\uE8C1",




"MATERIAL_SETTINGS_INPUT_HDMI": "\uE8C2",




"MATERIAL_SETTINGS_INPUT_SVIDEO": "\uE8C3",




"MATERIAL_SETTINGS_OVERSCAN": "\uE8C4",




"MATERIAL_SETTINGS_PHONE": "\uE8C5",




"MATERIAL_SETTINGS_POWER": "\uE8C6",




"MATERIAL_SETTINGS_REMOTE": "\uE8C7",




"MATERIAL_SETTINGS_SYSTEM_DAYDREAM": "\uE1C3",




"MATERIAL_SETTINGS_VOICE": "\uE8C8",




"MATERIAL_SHARE": "\uE80D",




"MATERIAL_SHOP": "\uE8C9",




"MATERIAL_SHOP_TWO": "\uE8CA",




"MATERIAL_SHOPPING_BASKET": "\uE8CB",




"MATERIAL_SHOPPING_CART": "\uE8CC",




"MATERIAL_SHORT_TEXT": "\uE261",




"MATERIAL_SHOW_CHART": "\uE6E1",




"MATERIAL_SHUFFLE": "\uE043",




"MATERIAL_SIGNAL_CELLULAR_4_BAR": "\uE1C8",




"MATERIAL_SIGNAL_CELLULAR_CONNECTED_NO_INTERNET_4_BAR": "\uE1CD",




"MATERIAL_SIGNAL_CELLULAR_NO_SIM": "\uE1CE",




"MATERIAL_SIGNAL_CELLULAR_NULL": "\uE1CF",




"MATERIAL_SIGNAL_CELLULAR_OFF": "\uE1D0",




"MATERIAL_SIGNAL_WIFI_4_BAR": "\uE1D8",




"MATERIAL_SIGNAL_WIFI_4_BAR_LOCK": "\uE1D9",




"MATERIAL_SIGNAL_WIFI_OFF": "\uE1DA",




"MATERIAL_SIM_CARD": "\uE32B",




"MATERIAL_SIM_CARD_ALERT": "\uE624",




"MATERIAL_SKIP_NEXT": "\uE044",




"MATERIAL_SKIP_PREVIOUS": "\uE045",




"MATERIAL_SLIDESHOW": "\uE41B",




"MATERIAL_SLOW_MOTION_VIDEO": "\uE068",




"MATERIAL_SMARTPHONE": "\uE32C",




"MATERIAL_SMOKE_FREE": "\uEB4A",




"MATERIAL_SMOKING_ROOMS": "\uEB4B",




"MATERIAL_SMS": "\uE625",




"MATERIAL_SMS_FAILED": "\uE626",




"MATERIAL_SNOOZE": "\uE046",




"MATERIAL_SORT": "\uE164",




"MATERIAL_SORT_BY_ALPHA": "\uE053",




"MATERIAL_SPA": "\uEB4C",




"MATERIAL_SPACE_BAR": "\uE256",




"MATERIAL_SPEAKER": "\uE32D",




"MATERIAL_SPEAKER_GROUP": "\uE32E",




"MATERIAL_SPEAKER_NOTES": "\uE8CD",




"MATERIAL_SPEAKER_NOTES_OFF": "\uE92A",




"MATERIAL_SPEAKER_PHONE": "\uE0D2",




"MATERIAL_SPELLCHECK": "\uE8CE",




"MATERIAL_STAR": "\uE838",




"MATERIAL_STAR_BORDER": "\uE83A",




"MATERIAL_STAR_HALF": "\uE839",




"MATERIAL_STARS": "\uE8D0",




"MATERIAL_STAY_CURRENT_LANDSCAPE": "\uE0D3",




"MATERIAL_STAY_CURRENT_PORTRAIT": "\uE0D4",




"MATERIAL_STAY_PRIMARY_LANDSCAPE": "\uE0D5",




"MATERIAL_STAY_PRIMARY_PORTRAIT": "\uE0D6",




"MATERIAL_STOP": "\uE047",




"MATERIAL_STOP_SCREEN_SHARE": "\uE0E3",




"MATERIAL_STORAGE": "\uE1DB",




"MATERIAL_STORE": "\uE8D1",




"MATERIAL_STORE_MALL_DIRECTORY": "\uE563",




"MATERIAL_STRAIGHTEN": "\uE41C",




"MATERIAL_STREETVIEW": "\uE56E",




"MATERIAL_STRIKETHROUGH_S": "\uE257",




"MATERIAL_STYLE": "\uE41D",




"MATERIAL_SUBDIRECTORY_ARROW_LEFT": "\uE5D9",




"MATERIAL_SUBDIRECTORY_ARROW_RIGHT": "\uE5DA",




"MATERIAL_SUBJECT": "\uE8D2",




"MATERIAL_SUBSCRIPTIONS": "\uE064",




"MATERIAL_SUBTITLES": "\uE048",




"MATERIAL_SUBWAY": "\uE56F",




"MATERIAL_SUPERVISOR_ACCOUNT": "\uE8D3",




"MATERIAL_SURROUND_SOUND": "\uE049",




"MATERIAL_SWAP_CALLS": "\uE0D7",




"MATERIAL_SWAP_HORIZ": "\uE8D4",




"MATERIAL_SWAP_VERT": "\uE8D5",




"MATERIAL_SWAP_VERTICAL_CIRCLE": "\uE8D6",




"MATERIAL_SWITCH_CAMERA": "\uE41E",




"MATERIAL_SWITCH_VIDEO": "\uE41F",




"MATERIAL_SYNC": "\uE627",




"MATERIAL_SYNC_DISABLED": "\uE628",




"MATERIAL_SYNC_PROBLEM": "\uE629",




"MATERIAL_SYSTEM_UPDATE": "\uE62A",




"MATERIAL_SYSTEM_UPDATE_ALT": "\uE8D7",




"MATERIAL_TAB": "\uE8D8",




"MATERIAL_TAB_UNSELECTED": "\uE8D9",




"MATERIAL_TABLET": "\uE32F",




"MATERIAL_TABLET_ANDROID": "\uE330",




"MATERIAL_TABLET_MAC": "\uE331",




"MATERIAL_TAG_FACES": "\uE420",




"MATERIAL_TAP_AND_PLAY": "\uE62B",




"MATERIAL_TERRAIN": "\uE564",




"MATERIAL_TEXT_FIELDS": "\uE262",




"MATERIAL_TEXT_FORMAT": "\uE165",




"MATERIAL_TEXTSMS": "\uE0D8",




"MATERIAL_TEXTURE": "\uE421",




"MATERIAL_THEATERS": "\uE8DA",




"MATERIAL_THUMB_DOWN": "\uE8DB",




"MATERIAL_THUMB_UP": "\uE8DC",




"MATERIAL_THUMBS_UP_DOWN": "\uE8DD",




"MATERIAL_TIME_TO_LEAVE": "\uE62C",




"MATERIAL_TIMELAPSE": "\uE422",




"MATERIAL_TIMELINE": "\uE922",




"MATERIAL_TIMER": "\uE425",




"MATERIAL_TIMER_10": "\uE423",




"MATERIAL_TIMER_3": "\uE424",




"MATERIAL_TIMER_OFF": "\uE426",




"MATERIAL_TITLE": "\uE264",




"MATERIAL_TOC": "\uE8DE",




"MATERIAL_TODAY": "\uE8DF",




"MATERIAL_TOLL": "\uE8E0",




"MATERIAL_TONALITY": "\uE427",




"MATERIAL_TOUCH_APP": "\uE913",




"MATERIAL_TOYS": "\uE332",




"MATERIAL_TRACK_CHANGES": "\uE8E1",




"MATERIAL_TRAFFIC": "\uE565",




"MATERIAL_TRAIN": "\uE570",




"MATERIAL_TRAM": "\uE571",




"MATERIAL_TRANSFER_WITHIN_A_STATION": "\uE572",




"MATERIAL_TRANSFORM": "\uE428",




"MATERIAL_TRANSLATE": "\uE8E2",




"MATERIAL_TRENDING_DOWN": "\uE8E3",




"MATERIAL_TRENDING_FLAT": "\uE8E4",




"MATERIAL_TRENDING_UP": "\uE8E5",




"MATERIAL_TUNE": "\uE429",




"MATERIAL_TURNED_IN": "\uE8E6",




"MATERIAL_TURNED_IN_NOT": "\uE8E7",




"MATERIAL_TV": "\uE333",




"MATERIAL_UNARCHIVE": "\uE169",




"MATERIAL_UNDO": "\uE166",




"MATERIAL_UNFOLD_LESS": "\uE5D6",




"MATERIAL_UNFOLD_MORE": "\uE5D7",




"MATERIAL_UPDATE": "\uE923",




"MATERIAL_USB": "\uE1E0",




"MATERIAL_VERIFIED_USER": "\uE8E8",




"MATERIAL_VERTICAL_ALIGN_BOTTOM": "\uE258",




"MATERIAL_VERTICAL_ALIGN_CENTER": "\uE259",




"MATERIAL_VERTICAL_ALIGN_TOP": "\uE25A",




"MATERIAL_VIBRATION": "\uE62D",




"MATERIAL_VIDEO_CALL": "\uE070",




"MATERIAL_VIDEO_LABEL": "\uE071",




"MATERIAL_VIDEO_LIBRARY": "\uE04A",




"MATERIAL_VIDEOCAM": "\uE04B",




"MATERIAL_VIDEOCAM_OFF": "\uE04C",




"MATERIAL_VIDEOGAME_ASSET": "\uE338",




"MATERIAL_VIEW_AGENDA": "\uE8E9",




"MATERIAL_VIEW_ARRAY": "\uE8EA",




"MATERIAL_VIEW_CAROUSEL": "\uE8EB",




"MATERIAL_VIEW_COLUMN": "\uE8EC",




"MATERIAL_VIEW_COMFY": "\uE42A",




"MATERIAL_VIEW_COMPACT": "\uE42B",




"MATERIAL_VIEW_DAY": "\uE8ED",




"MATERIAL_VIEW_HEADLINE": "\uE8EE",




"MATERIAL_VIEW_LIST": "\uE8EF",




"MATERIAL_VIEW_MODULE": "\uE8F0",




"MATERIAL_VIEW_QUILT": "\uE8F1",




"MATERIAL_VIEW_STREAM": "\uE8F2",




"MATERIAL_VIEW_WEEK": "\uE8F3",




"MATERIAL_VIGNETTE": "\uE435",




"MATERIAL_VISIBILITY": "\uE8F4",




"MATERIAL_VISIBILITY_OFF": "\uE8F5",




"MATERIAL_VOICE_CHAT": "\uE62E",




"MATERIAL_VOICEMAIL": "\uE0D9",




"MATERIAL_VOLUME_DOWN": "\uE04D",




"MATERIAL_VOLUME_MUTE": "\uE04E",




"MATERIAL_VOLUME_OFF": "\uE04F",




"MATERIAL_VOLUME_UP": "\uE050",




"MATERIAL_VPN_KEY": "\uE0DA",




"MATERIAL_VPN_LOCK": "\uE62F",




"MATERIAL_WALLPAPER": "\uE1BC",




"MATERIAL_WARNING": "\uE002",




"MATERIAL_WATCH": "\uE334",




"MATERIAL_WATCH_LATER": "\uE924",




"MATERIAL_WB_AUTO": "\uE42C",




"MATERIAL_WB_CLOUDY": "\uE42D",




"MATERIAL_WB_INCANDESCENT": "\uE42E",




"MATERIAL_WB_IRIDESCENT": "\uE436",




"MATERIAL_WB_SUNNY": "\uE430",




"MATERIAL_WC": "\uE63D",




"MATERIAL_WEB": "\uE051",




"MATERIAL_WEB_ASSET": "\uE069",




"MATERIAL_WEEKEND": "\uE16B",




"MATERIAL_WHATSHOT": "\uE80E",




"MATERIAL_WIDGETS": "\uE1BD",




"MATERIAL_WIFI": "\uE63E",




"MATERIAL_WIFI_LOCK": "\uE1E1",




"MATERIAL_WIFI_TETHERING": "\uE1E2",




"MATERIAL_WORK": "\uE8F9",




"MATERIAL_WRAP_TEXT": "\uE25B",




"MATERIAL_YOUTUBE_SEARCHED_FOR": "\uE8FA",




"MATERIAL_ZOOM_IN": "\uE8FF",




"MATERIAL_ZOOM_OUT": "\uE900",





"MATERIAL_ZOOM_OUT_MAP": "\uE56B",






"MATERIAL_10K": "\uE951",





"MATERIAL_10MP": "\uE952",





"MATERIAL_11MP": "\uE953",





"MATERIAL_12MP": "\uE954",





"MATERIAL_13MP": "\uE955",





"MATERIAL_14MP": "\uE956",





"MATERIAL_15MP": "\uE957",





"MATERIAL_16MP": "\uE958",





"MATERIAL_17MP": "\uE959",





"MATERIAL_18MP": "\uE95A",





"MATERIAL_19MP": "\uE95B",





"MATERIAL_1K": "\uE95C",





"MATERIAL_1K_PLUS": "\uE95D",





"MATERIAL_20MP": "\uE95E",





"MATERIAL_21MP": "\uE95F",





"MATERIAL_22MP": "\uE960",





"MATERIAL_23MP": "\uE961",





"MATERIAL_24MP": "\uE962",





"MATERIAL_2K": "\uE963",





"MATERIAL_2K_PLUS": "\uE964",





"MATERIAL_2MP": "\uE965",





"MATERIAL_360": "\uE577",





"MATERIAL_3K": "\uE966",





"MATERIAL_3K_PLUS": "\uE967",





"MATERIAL_3MP": "\uE968",





"MATERIAL_4K": "\uE072",





"MATERIAL_4K_PLUS": "\uE969",





"MATERIAL_4MP": "\uE96A",





"MATERIAL_5K": "\uE96B",





"MATERIAL_5K_PLUS": "\uE96C",





"MATERIAL_5MP": "\uE96D",





"MATERIAL_6K": "\uE96E",





"MATERIAL_6K_PLUS": "\uE96F",





"MATERIAL_6MP": "\uE970",





"MATERIAL_7K": "\uE971",





"MATERIAL_7K_PLUS": "\uE972",





"MATERIAL_7MP": "\uE973",





"MATERIAL_8K": "\uE974",





"MATERIAL_8K_PLUS": "\uE975",





"MATERIAL_8MP": "\uE976",





"MATERIAL_9K": "\uE977",





"MATERIAL_9K_PLUS": "\uE978",





"MATERIAL_9MP": "\uE979",





"MATERIAL_ACCESSIBILITY_NEW": "\uE92C",





"MATERIAL_ACCESSIBLE_FORWARD": "\uE934",





"MATERIAL_ACCOUNT_TREE": "\uE97A",





"MATERIAL_ADD_CALL": "\uE0E8",





"MATERIAL_ADD_CHART": "\uE97B",





"MATERIAL_ADD_COMMENT": "\uE266",





"MATERIAL_ADD_IC_CALL": "\uE97C",





"MATERIAL_ADD_LINK": "\uE178",





"MATERIAL_ADD_MODERATOR": "\uE97D",





"MATERIAL_ADD_PHOTO_ALTERNATE": "\uE43E",





"MATERIAL_ADD_TO_HOME_SCREEN": "\uE1FE",





"MATERIAL_AIRPLANEMODE_OFF": "\uE194",





"MATERIAL_AIRPLANEMODE_ON": "\uE195",





"MATERIAL_ALL_INBOX": "\uE97F",





"MATERIAL_ALTERNATE_EMAIL": "\uE0E6",





"MATERIAL_AMP_STORIES": "\uEA13",





"MATERIAL_APARTMENT": "\uEA40",





"MATERIAL_APPROVAL": "\uE982",





"MATERIAL_ARROW_BACK_IOS": "\uE5E0",





"MATERIAL_ARROW_FORWARD_IOS": "\uE5E1",





"MATERIAL_ARROW_LEFT": "\uE5DE",





"MATERIAL_ARROW_RIGHT_ALT": "\uE941",





"MATERIAL_ARROW_RIGHT": "\uE5DF",





"MATERIAL_ASSISTANT_DIRECTION": "\uE988",





"MATERIAL_ASSISTANT_NAVIGATION": "\uE989",





"MATERIAL_ATM": "\uE573",





"MATERIAL_ATTRACTIONS": "\uEA52",





"MATERIAL_BADGE": "\uEA67",





"MATERIAL_BAKERY_DINING": "\uEA53",





"MATERIAL_BALLOT": "\uE172",





"MATERIAL_BAR_CHART": "\uE26B",





"MATERIAL_BATHTUB": "\uEA41",





"MATERIAL_BOLT": "\uEA0B",





"MATERIAL_BOOKMARK_OUTLINE": "\uE867",





"MATERIAL_BOOKMARKS": "\uE98B",





"MATERIAL_BREAKFAST_DINING": "\uEA54",





"MATERIAL_BRUNCH_DINING": "\uEA73",





"MATERIAL_BUS_ALERT": "\uE98F",





"MATERIAL_CALENDAR_TODAY": "\uE935",





"MATERIAL_CALENDAR_VIEW_DAY": "\uE936",





"MATERIAL_CANCEL_PRESENTATION": "\uE0E9",





"MATERIAL_CANCEL_SCHEDULE_SEND": "\uEA39",





"MATERIAL_CAR_RENTAL": "\uEA55",





"MATERIAL_CAR_REPAIR": "\uEA56",





"MATERIAL_CASES": "\uE992",





"MATERIAL_CATEGORY": "\uE574",





"MATERIAL_CELEBRATION": "\uEA65",





"MATERIAL_CELL_WIFI": "\uE0EC",





"MATERIAL_CHECK_CIRCLE_OUTLINE": "\uE92D",





"MATERIAL_CIRCLE_NOTIFICATIONS": "\uE994",





"MATERIAL_CLOSED_CAPTION_OFF": "\uE996",





"MATERIAL_COMMUTE": "\uE940",





"MATERIAL_COMPASS_CALIBRATION": "\uE57C",





"MATERIAL_COMPRESS": "\uE94D",





"MATERIAL_CONFIRMATION_NUM": "\uE638",





"MATERIAL_CONNECTED_TV": "\uE998",





"MATERIAL_CONTACTLESS": "\uEA71",





"MATERIAL_CONTACT_SUPPORT": "\uE94C",





"MATERIAL_CONTROL_CAMERA": "\uE074",





"MATERIAL_DANGEROUS": "\uE99A",





"MATERIAL_DASHBOARD_CUSTOMIZE": "\uE99B",





"MATERIAL_DECK": "\uEA42",





"MATERIAL_DELETE_OUTLINE": "\uE92E",





"MATERIAL_DELIVERY_DINING": "\uEA72",





"MATERIAL_DEPARTURE_BOARD": "\uE576",





"MATERIAL_DESKTOP_ACCESS_DISABLED": "\uE99D",





"MATERIAL_DEVICE_THERMOSTAT": "\uE1FF",





"MATERIAL_DEVICE_UNKNOWN": "\uE339",





"MATERIAL_DINNER_DINING": "\uEA57",





"MATERIAL_DIRECTIONS_FERRY": "\uE532",





"MATERIAL_DIRECTIONS_TRAIN": "\uE534",





"MATERIAL_DND_FORWARDSLASH": "\uE611",





"MATERIAL_DOMAIN_DISABLED": "\uE0EF",





"MATERIAL_DONE_OUTLINE": "\uE92F",





"MATERIAL_DOUBLE_ARROW": "\uEA50",





"MATERIAL_DRAG_INDICATOR": "\uE945",





"MATERIAL_DRIVE_FILE_MOVE_OUTLINE": "\uE9A1",





"MATERIAL_DRIVE_FILE_RENAME_OUTLINE": "\uE9A2",





"MATERIAL_DRIVE_FOLDER_UPLOAD": "\uE9A3",





"MATERIAL_DRY_CLEANING": "\uEA58",





"MATERIAL_DUO": "\uE9A5",





"MATERIAL_DYNAMIC_FEED": "\uEA14",





"MATERIAL_ECO": "\uEA35",





"MATERIAL_EDIT_ATTRIBUTES": "\uE578",





"MATERIAL_EDIT_OFF": "\uE950",





"MATERIAL_EMOJI_EMOTIONS": "\uEA22",





"MATERIAL_EMOJI_EVENTS": "\uEA23",





"MATERIAL_EMOJI_FLAGS": "\uEA1A",





"MATERIAL_EMOJI_FOOD_BEVERAGE": "\uEA1B",





"MATERIAL_EMOJI_NATURE": "\uEA1C",





"MATERIAL_EMOJI_OBJECTS": "\uEA24",





"MATERIAL_EMOJI_PEOPLE": "\uEA1D",





"MATERIAL_EMOJI_SYMBOLS": "\uEA1E",





"MATERIAL_EMOJI_TRANSPORTATION": "\uEA1F",





"MATERIAL_ENHANCE_PHOTO_TRANSLATE": "\uE8FC",





"MATERIAL_EURO": "\uEA15",





"MATERIAL_EXPAND": "\uE94F",





"MATERIAL_EXPLORE_OFF": "\uE9A8",





"MATERIAL_EXPOSURE_MINUS_1": "\uE3CB",





"MATERIAL_EXPOSURE_MINUS_2": "\uE3CC",





"MATERIAL_FASTFOOD": "\uE57A",





"MATERIAL_FAVORITE_OUTLINE": "\uE87E",





"MATERIAL_FESTIVAL": "\uEA68",





"MATERIAL_FILE_COPY": "\uE173",





"MATERIAL_FILE_DOWNLOAD_DONE": "\uE9AA",





"MATERIAL_FILE_PRESENT": "\uEA0E",





"MATERIAL_FILTER_LIST_ALT": "\uE94E",





"MATERIAL_FIREPLACE": "\uEA43",





"MATERIAL_FIT_SCREEN": "\uEA10",





"MATERIAL_FLIP_CAMERA_ANDROID": "\uEA37",





"MATERIAL_FLIP_CAMERA_IOS": "\uEA38",





"MATERIAL_FORMAT_LIST_NUMBERED_RTL": "\uE267",





"MATERIAL_FORMAT_UNDERLINE": "\uE249",





"MATERIAL_GOAT": "\uDBFF",





"MATERIAL_GRID_VIEW": "\uE9B0",





"MATERIAL_HAIL": "\uE9B1",





"MATERIAL_HARDWARE": "\uEA59",





"MATERIAL_HEADSET_OFF": "\uE33A",





"MATERIAL_HEIGHT": "\uEA16",





"MATERIAL_HIGHLIGHT_REMOVE": "\uE888",





"MATERIAL_HOME_FILLED": "\uE9B2",





"MATERIAL_HOME_WORK": "\uEA09",





"MATERIAL_HORIZONTAL_SPLIT": "\uE947",





"MATERIAL_HOUSE": "\uEA44",





"MATERIAL_HOW_TO_REG": "\uE174",





"MATERIAL_HOW_TO_VOTE": "\uE175",





"MATERIAL_ICECREAM": "\uEA69",





"MATERIAL_IMAGE_SEARCH": "\uE43F",





"MATERIAL_IMAGESEARCH_ROLLER": "\uE9B4",





"MATERIAL_INSERT_CHART_OUTLINED": "\uE26A",





"MATERIAL_INVENTORY": "\uE179",





"MATERIAL_INVERT_COLORS_ON": "\uE891",





"MATERIAL_KEYBOARD_CONTROL": "\uE5D3",





"MATERIAL_KING_BED": "\uEA45",





"MATERIAL_LABEL_IMPORTANT": "\uE937",





"MATERIAL_LABEL_IMPORTANT_OUTLINE": "\uE948",





"MATERIAL_LABEL_OFF": "\uE9B6",





"MATERIAL_LIBRARY_ADD_CHECK": "\uE9B7",





"MATERIAL_LIGHTBULB": "\uE0F0",





"MATERIAL_LINK_OFF": "\uE16F",





"MATERIAL_LIQUOR": "\uEA60",





"MATERIAL_LIST_ALT": "\uE0EE",





"MATERIAL_LOCAL_ATTRACTION": "\uE53F",





"MATERIAL_LOCAL_PRINT_SHOP": "\uE555",





"MATERIAL_LOCAL_RESTAURANT": "\uE556",





"MATERIAL_LOCATION_HISTORY": "\uE55A",





"MATERIAL_LOGOUT": "\uE9BA",





"MATERIAL_LUNCH_DINING": "\uEA61",





"MATERIAL_MARGIN": "\uE9BB",





"MATERIAL_MARK_AS_UNREAD": "\uE9BC",





"MATERIAL_MAXIMIZE": "\uE930",





"MATERIAL_MEETING_ROOM": "\uEB4F",





"MATERIAL_MENU_BOOK": "\uEA19",





"MATERIAL_MENU_OPEN": "\uE9BD",





"MATERIAL_MESSENGER": "\uE0CA",





"MATERIAL_MESSENGER_OUTLINE": "\uE0CB",





"MATERIAL_MINIMIZE": "\uE931",





"MATERIAL_MISSED_VIDEO_CALL": "\uE073",





"MATERIAL_MOBILE_FRIENDLY": "\uE200",





"MATERIAL_MOBILE_OFF": "\uE201",





"MATERIAL_MOBILE_SCREEN_SHARE": "\uE0E7",





"MATERIAL_MONEY": "\uE57D",





"MATERIAL_MP": "\uE9C3",





"MATERIAL_MULTITRACK_AUDIO": "\uE1B8",





"MATERIAL_MUSEUM": "\uEA36",





"MATERIAL_MUSIC_OFF": "\uE440",





"MATERIAL_MY_LIBRARY_ADD": "\uE02E",





"MATERIAL_MY_LIBRARY_BOOKS": "\uE02F",





"MATERIAL_MY_LIBRARY_MUSIC": "\uE030",





"MATERIAL_NIGHTLIFE": "\uEA62",





"MATERIAL_NIGHTS_STAY": "\uEA46",





"MATERIAL_NO_MEETING_ROOM": "\uEB4E",





"MATERIAL_NOTES": "\uE26C",





"MATERIAL_NOTIFICATION_IMPORTANT": "\uE004",





"MATERIAL_NOTIFICATIONS_ON": "\uE7F7",





"MATERIAL_NOT_LISTED_LOCATION": "\uE575",





"MATERIAL_NOW_WALLPAPER": "\uE1BC",





"MATERIAL_NOW_WIDGETS": "\uE1BD",





"MATERIAL_OFFLINE_BOLT": "\uE932",





"MATERIAL_OFFLINE_SHARE": "\uE9C5",





"MATERIAL_OUTDOOR_GRILL": "\uEA47",





"MATERIAL_OUTLINED_FLAG": "\uE16E",





"MATERIAL_PADDING": "\uE9C8",





"MATERIAL_PANORAMA_FISHEYE": "\uE40C",





"MATERIAL_PANORAMA_PHOTOSPHERE": "\uE9C9",





"MATERIAL_PANORAMA_PHOTOSPHERE_SELECT": "\uE9CA",





"MATERIAL_PARK": "\uEA63",





"MATERIAL_PAUSE_PRESENTATION": "\uE0EA",





"MATERIAL_PEOPLE_ALT": "\uEA21",





"MATERIAL_PERM_CONTACT_CAL": "\uE8A3",





"MATERIAL_PERM_DEVICE_INFO": "\uE8A5",





"MATERIAL_PERSON_ADD_DISABLED": "\uE9CB",





"MATERIAL_PHONE_CALLBACK": "\uE649",





"MATERIAL_PHONE_DISABLED": "\uE9CC",





"MATERIAL_PHONE_ENABLED": "\uE9CD",





"MATERIAL_PIVOT_TABLE_CHART": "\uE9CE",





"MATERIAL_PLAY_CIRCLE_FILL": "\uE038",





"MATERIAL_POLICY": "\uEA17",





"MATERIAL_POST_ADD": "\uEA20",





"MATERIAL_POWER_OFF": "\uE646",





"MATERIAL_PRINT_DISABLED": "\uE9CF",





"MATERIAL_QUICK_CONTACTS_DIALER": "\uE0CF",





"MATERIAL_QUICK_CONTACTS_MAIL": "\uE0D0",





"MATERIAL_RADIO_BUTTON_OFF": "\uE836",





"MATERIAL_RADIO_BUTTON_ON": "\uE837",





"MATERIAL_RAILWAY_ALERT": "\uE9D1",





"MATERIAL_RAMEN_DINING": "\uEA64",





"MATERIAL_RECOMMEND": "\uE9D2",





"MATERIAL_REMOVE_DONE": "\uE9D3",





"MATERIAL_REMOVE_MODERATOR": "\uE9D4",





"MATERIAL_REPEAT_ON": "\uE9D6",





"MATERIAL_REPEAT_ONE_ON": "\uE9D7",





"MATERIAL_REPLAY_CIRCLE_FILLED": "\uE9D8",





"MATERIAL_REPORT_OFF": "\uE170",





"MATERIAL_RESET_TV": "\uE9D9",





"MATERIAL_RESTORE_FROM_TRASH": "\uE938",





"MATERIAL_RTT": "\uE9AD",





"MATERIAL_SAVE_ALT": "\uE171",





"MATERIAL_SAVED_SEARCH": "\uEA11",





"MATERIAL_SCATTER_PLOT": "\uE268",





"MATERIAL_SCHEDULE_SEND": "\uEA0A",





"MATERIAL_SCORE": "\uE269",





"MATERIAL_SD": "\uE9DD",





"MATERIAL_SEGMENT": "\uE94B",





"MATERIAL_SEND_AND_ARCHIVE": "\uEA0C",





"MATERIAL_SENTIMENT_SATISFIED_ALT": "\uE0ED",





"MATERIAL_SETTINGS_DISPLAY": "\uE8BD",





"MATERIAL_SHIELD": "\uE9E0",





"MATERIAL_SHUFFLE_ON": "\uE9E1",





"MATERIAL_SHUTTER_SPEED": "\uE43D",





"MATERIAL_SIGNAL_CELLULAR_ALT": "\uE202",





"MATERIAL_SINGLE_BED": "\uEA48",





"MATERIAL_SPEED": "\uE9E4",





"MATERIAL_SPORTS_BASEBALL": "\uEA51",





"MATERIAL_SPORTS_BASKETBALL": "\uEA26",





"MATERIAL_SPORTS_CRICKET": "\uEA27",





"MATERIAL_SPORTS": "\uEA30",





"MATERIAL_SPORTS_ESPORTS": "\uEA28",





"MATERIAL_SPORTS_FOOTBALL": "\uEA29",





"MATERIAL_SPORTS_GOLF": "\uEA2A",





"MATERIAL_SPORTS_HANDBALL": "\uEA33",





"MATERIAL_SPORTS_HOCKEY": "\uEA2B",





"MATERIAL_SPORTS_KABADDI": "\uEA34",





"MATERIAL_SPORTS_MMA": "\uEA2C",





"MATERIAL_SPORTS_MOTORSPORTS": "\uEA2D",





"MATERIAL_SPORTS_RUGBY": "\uEA2E",





"MATERIAL_SPORTS_SOCCER": "\uEA2F",





"MATERIAL_SPORTS_TENNIS": "\uEA32",





"MATERIAL_SPORTS_VOLLEYBALL": "\uEA31",





"MATERIAL_SQUARE_FOOT": "\uEA49",





"MATERIAL_STACKED_BAR_CHART": "\uE9E6",





"MATERIAL_STAR_OUTLINE": "\uE83A",





"MATERIAL_STOREFRONT": "\uEA12",





"MATERIAL_STREAM": "\uE9E9",





"MATERIAL_SUPERVISED_USER_CIRCLE": "\uE939",





"MATERIAL_SWAP_HORIZONTAL_CIRCLE": "\uE933",





"MATERIAL_SWAP_VERT_CIRCLE": "\uE8D6",





"MATERIAL_SWIPE": "\uE9EC",





"MATERIAL_SWITCH_ACCOUNT": "\uE9ED",





"MATERIAL_SYNC_ALT": "\uEA18",





"MATERIAL_SYSTEM_UPDATE_TV": "\uE8D7",





"MATERIAL_TABLE_CHART": "\uE265",





"MATERIAL_TAG": "\uE9EF",





"MATERIAL_TAKEOUT_DINING": "\uEA74",





"MATERIAL_TEXT_ROTATE_UP": "\uE93A",





"MATERIAL_TEXT_ROTATE_VERTICAL": "\uE93B",





"MATERIAL_TEXT_ROTATION_ANGLEDOWN": "\uE93C",





"MATERIAL_TEXT_ROTATION_ANGLEUP": "\uE93D",





"MATERIAL_TEXT_ROTATION_DOWN": "\uE93E",





"MATERIAL_TEXT_ROTATION_NONE": "\uE93F",





"MATERIAL_THEATER_COMEDY": "\uEA66",





"MATERIAL_THUMB_DOWN_ALT": "\uE816",





"MATERIAL_THUMB_DOWN_OFF_ALT": "\uE9F2",





"MATERIAL_THUMB_UP_ALT": "\uE817",





"MATERIAL_THUMB_UP_OFF_ALT": "\uE9F3",





"MATERIAL_TOGGLE_OFF": "\uE9F5",





"MATERIAL_TOGGLE_ON": "\uE9F6",





"MATERIAL_TRANSIT_ENTEREXIT": "\uE579",





"MATERIAL_TRENDING_NEUTRAL": "\uE8E4",





"MATERIAL_TRIP_ORIGIN": "\uE57B",





"MATERIAL_TV_OFF": "\uE647",





"MATERIAL_TWO_WHEELER": "\uE9F9",





"MATERIAL_UNSUBSCRIBE": "\uE0EB",





"MATERIAL_UPLOAD_FILE": "\uE9FC",





"MATERIAL_VERTICAL_SPLIT": "\uE949",





"MATERIAL_VIDEO_COLLECTION": "\uE04A",





"MATERIAL_VIEW_COMFORTABLE": "\uE42A",





"MATERIAL_VIEW_IN_AR": "\uE9FE",





"MATERIAL_VOICE_OVER_OFF": "\uE94A",





"MATERIAL_VOLUNTEER_ACTIVISM": "\uEA70",





"MATERIAL_WALLET_GIFTCARD": "\uE8F6",





"MATERIAL_WALLET_MEMBERSHIP": "\uE8F7",





"MATERIAL_WALLET_TRAVEL": "\uE8F8",





"MATERIAL_WATERFALL_CHART": "\uEA00",





"MATERIAL_WAVES": "\uE176",





"MATERIAL_WB_SHADE": "\uEA01",





"MATERIAL_WB_TWIGHLIGHT": "\uEA02",





"MATERIAL_WHERE_TO_VOTE": "\uE177",





"MATERIAL_WIFI_OFF": "\uE648",





"MATERIAL_WORK_OFF": "\uE942",





"MATERIAL_WORK_OUTLINE": "\uE943",





"MATERIAL_WORKSPACES_FILLED": "\uEA0D",





"MATERIAL_WORKSPACES_OUTLINE": "\uEA0F"}]
    
